LICENSE
MANIFEST.in
README.md
setup.py
bin/locale_alg
sdp_clustering/__init__.py
sdp_clustering/models.py
sdp_clustering.egg-info/PKG-INFO
sdp_clustering.egg-info/SOURCES.txt
sdp_clustering.egg-info/dependency_links.txt
sdp_clustering.egg-info/not-zip-safe
sdp_clustering.egg-info/requires.txt
sdp_clustering.egg-info/top_level.txt
src/cluster.cpp
src/cluster.h
src/pybind.cpp
third_party/pybind11/include/pybind11/attr.h
third_party/pybind11/include/pybind11/buffer_info.h
third_party/pybind11/include/pybind11/cast.h
third_party/pybind11/include/pybind11/chrono.h
third_party/pybind11/include/pybind11/common.h
third_party/pybind11/include/pybind11/complex.h
third_party/pybind11/include/pybind11/eigen.h
third_party/pybind11/include/pybind11/embed.h
third_party/pybind11/include/pybind11/eval.h
third_party/pybind11/include/pybind11/functional.h
third_party/pybind11/include/pybind11/iostream.h
third_party/pybind11/include/pybind11/numpy.h
third_party/pybind11/include/pybind11/operators.h
third_party/pybind11/include/pybind11/options.h
third_party/pybind11/include/pybind11/pybind11.h
third_party/pybind11/include/pybind11/pytypes.h
third_party/pybind11/include/pybind11/stl.h
third_party/pybind11/include/pybind11/stl_bind.h
third_party/pybind11/include/pybind11/detail/class.h
third_party/pybind11/include/pybind11/detail/common.h
third_party/pybind11/include/pybind11/detail/descr.h
third_party/pybind11/include/pybind11/detail/init.h
third_party/pybind11/include/pybind11/detail/internals.h
third_party/pybind11/include/pybind11/detail/typeid.h
third_party/pybind11/pybind11/__init__.py
third_party/pybind11/pybind11/__main__.py
third_party/pybind11/pybind11/_version.py
third_party/pybind11/pybind11/commands.py
third_party/pybind11/pybind11/setup_helpers.py