Metadata-Version: 2.1
Name: sdp-clustering
Version: 0.0.1
Summary: SDP-based clustering by maximum modularity
Home-page: https://github.com/locuslab/sdp_clustering
Author: Po-Wei Wang
Author-email: poweiw@cs.cmu.edu
License: UNKNOWN
Platform: UNKNOWN
Classifier: License :: OSI Approved :: MIT License
Provides-Extra: test
